pytest_unittest_filter.py
pytest_unittest_filter-0.2.1.dist-info/LICENSE
pytest_unittest_filter-0.2.1.dist-info/METADATA
pytest_unittest_filter-0.2.1.dist-info/WHEEL
pytest_unittest_filter-0.2.1.dist-info/entry_points.txt
pytest_unittest_filter-0.2.1.dist-info/top_level.txt
pytest_unittest_filter-0.2.1.dist-info/RECORD
